kub/__init__.py
kub/kub_utilities.py
kub-0.5.0.dist-info/LICENSE
kub-0.5.0.dist-info/METADATA
kub-0.5.0.dist-info/WHEEL
kub-0.5.0.dist-info/RECORD
